galaxy_utils/__init__.py
galaxy_utils/sequence/__init__.py
galaxy_utils/sequence/fasta.py
galaxy_utils/sequence/fastq.py
galaxy_utils/sequence/sequence.py
galaxy_utils/sequence/transform.py
galaxy_utils/sequence/vcf.py
galaxy_utils/sequence/scripts/__init__.py
galaxy_utils/sequence/scripts/fastq_combiner.py
galaxy_utils/sequence/scripts/fastq_filter.py
galaxy_utils/sequence/scripts/fastq_groomer.py
galaxy_utils/sequence/scripts/fastq_manipulation.py
galaxy_utils/sequence/scripts/fastq_masker_by_quality.py
galaxy_utils/sequence/scripts/fastq_paired_end_deinterlacer.py
galaxy_utils/sequence/scripts/fastq_paired_end_interlacer.py
galaxy_utils/sequence/scripts/fastq_paired_end_joiner.py
galaxy_utils/sequence/scripts/fastq_paired_end_splitter.py
galaxy_utils/sequence/scripts/fastq_stats.py
galaxy_utils/sequence/scripts/fastq_to_fasta.py
galaxy_utils/sequence/scripts/fastq_to_tabular.py
galaxy_utils/sequence/scripts/fastq_trimmer.py
galaxy_utils/sequence/scripts/fastq_trimmer_by_quality.py
galaxy_sequence_utils-1.2.0.dist-info/LICENSE
galaxy_sequence_utils-1.2.0.dist-info/METADATA
galaxy_sequence_utils-1.2.0.dist-info/WHEEL
galaxy_sequence_utils-1.2.0.dist-info/entry_points.txt
galaxy_sequence_utils-1.2.0.dist-info/top_level.txt
galaxy_sequence_utils-1.2.0.dist-info/RECORD
